Metadata-Version: 1.1
Name: distributions-srns
Version: 0.1
Summary: Probability distributions
Home-page: UNKNOWN
Author: srns
Author-email: UNKNOWN
License: UNKNOWN
Platform: UNKNOWN
Classifier: Programming Language :: Python :: 3
Classifier: License :: OSI Approved :: MIT License
Classifier: Operating System :: OS Independent
